pipe.py
pipe-1.6.0.dist-info/METADATA
pipe-1.6.0.dist-info/WHEEL
pipe-1.6.0.dist-info/top_level.txt
pipe-1.6.0.dist-info/RECORD
