Metadata-Version: 2.1
Name: pipe
Version: 1.6.0
Summary: Module enablig a sh like infix syntax (using pipes)
Home-page: https://github.com/JulienPalard/Pipe
Author: Julien Palard
Author-email: julien@palard.fr
License: MIT license
Download-URL: https://github.com/JulienPalard/Pipe/tarball/master
Platform: UNKNOWN
Classifier: Programming Language :: Python
Classifier: Programming Language :: Python :: 3
Classifier: Development Status :: 5 - Production/Stable
Classifier: Intended Audience :: Developers
Classifier: License :: OSI Approved :: BSD License
Classifier: Operating System :: OS Independent
Classifier: Topic :: Software Development
Classifier: Topic :: Software Development :: Libraries :: Python Modules
